LICENSE.rst
MANIFEST.in
README.rst
setup.py
bin/untrend
untrendy/__init__.py
untrendy/_untrendy.c
untrendy/tests.py
untrendy/untrendy.c
untrendy/untrendy.h
untrendy/untrendy.py
untrendy.egg-info/PKG-INFO
untrendy.egg-info/SOURCES.txt
untrendy.egg-info/dependency_links.txt
untrendy.egg-info/top_level.txt
untrendy/test_data/kplr010874614-2009131105131_llc.fits